{
  "person": [
	{
		"id": 1,
		"name": "Larissa",
		"surname": "Cabrera"
	},
	{
		"id": 2,
		"name": "Courtney",
		"surname": "Sanders"
	},
	{
		"id": 3,
		"name": "Camilla",
		"surname": "Ruiz"
	},
	{
		"id": 4,
		"name": "Jenna",
		"surname": "Santana"
	},
	{
		"id": 5,
		"name": "Aurelia",
		"surname": "Clark"
	},
	{
		"id": 6,
		"name": "Eaton",
		"surname": "Mullins"
	},
	{
		"id": 7,
		"name": "Aileen",
		"surname": "Clay"
	},
	{
		"id": 8,
		"name": "Gareth",
		"surname": "Dean"
	},
	{
		"id": 9,
		"name": "Vance",
		"surname": "Lott"
	},
	{
		"id": 10,
		"name": "Lacota",
		"surname": "Brewer"
	},
	{
		"id": 11,
		"name": "Aretha",
		"surname": "Hobbs"
	},
	{
		"id": 12,
		"name": "Wilma",
		"surname": "Davis"
	},
	{
		"id": 13,
		"name": "Hop",
		"surname": "Thomas"
	},
	{
		"id": 14,
		"name": "Ayanna",
		"surname": "Hamilton"
	},
	{
		"id": 15,
		"name": "Katell",
		"surname": "Montoya"
	},
	{
		"id": 16,
		"name": "Blaze",
		"surname": "Gilbert"
	},
	{
		"id": 17,
		"name": "Meghan",
		"surname": "Dejesus"
	},
	{
		"id": 18,
		"name": "Louis",
		"surname": "England"
	},
	{
		"id": 19,
		"name": "Meghan",
		"surname": "Howell"
	},
	{
		"id": 20,
		"name": "Kiayada",
		"surname": "Faulkner"
	},
	{
		"id": 21,
		"name": "Ezra",
		"surname": "Hampton"
	},
	{
		"id": 22,
		"name": "Jonah",
		"surname": "Gilbert"
	},
	{
		"id": 23,
		"name": "Calvin",
		"surname": "Buck"
	},
	{
		"id": 24,
		"name": "Reed",
		"surname": "Clay"
	},
	{
		"id": 25,
		"name": "Taylor",
		"surname": "Kelly"
	},
	{
		"id": 26,
		"name": "Faith",
		"surname": "Perry"
	},
	{
		"id": 27,
		"name": "Shoshana",
		"surname": "Edwards"
	},
	{
		"id": 28,
		"name": "Talon",
		"surname": "Adkins"
	},
	{
		"id": 29,
		"name": "Cody",
		"surname": "Rios"
	},
	{
		"id": 30,
		"name": "Leilani",
		"surname": "Boyle"
	},
	{
		"id": 31,
		"name": "Audrey",
		"surname": "Sawyer"
	},
	{
		"id": 32,
		"name": "Gretchen",
		"surname": "Ramsey"
	},
	{
		"id": 33,
		"name": "Jamal",
		"surname": "Valencia"
	},
	{
		"id": 34,
		"name": "Isabelle",
		"surname": "Contreras"
	},
	{
		"id": 35,
		"name": "Daniel",
		"surname": "Wall"
	},
	{
		"id": 36,
		"name": "Irene",
		"surname": "Carpenter"
	},
	{
		"id": 37,
		"name": "Yolanda",
		"surname": "Donaldson"
	},
	{
		"id": 38,
		"name": "Zelda",
		"surname": "Jackson"
	},
	{
		"id": 39,
		"name": "Michael",
		"surname": "Huffman"
	},
	{
		"id": 40,
		"name": "Oleg",
		"surname": "Talley"
	},
	{
		"id": 41,
		"name": "Talon",
		"surname": "Lucas"
	},
	{
		"id": 42,
		"name": "Coby",
		"surname": "Bartlett"
	},
	{
		"id": 43,
		"name": "Kevin",
		"surname": "Rhodes"
	},
	{
		"id": 44,
		"name": "Cora",
		"surname": "Brady"
	},
	{
		"id": 45,
		"name": "Leilani",
		"surname": "Maxwell"
	},
	{
		"id": 46,
		"name": "Quentin",
		"surname": "Ratliff"
	},
	{
		"id": 47,
		"name": "Bryar",
		"surname": "Larsen"
	},
	{
		"id": 48,
		"name": "Kibo",
		"surname": "Alford"
	},
	{
		"id": 49,
		"name": "Cailin",
		"surname": "Hicks"
	},
	{
		"id": 50,
		"name": "Florence",
		"surname": "William"
	},
	{
		"id": 51,
		"name": "Lynn",
		"surname": "Hopper"
	},
	{
		"id": 52,
		"name": "Molly",
		"surname": "Gaines"
	},
	{
		"id": 53,
		"name": "Demetria",
		"surname": "Gay"
	},
	{
		"id": 54,
		"name": "Lani",
		"surname": "Vazquez"
	},
	{
		"id": 55,
		"name": "Lee",
		"surname": "Gillespie"
	},
	{
		"id": 56,
		"name": "Dawn",
		"surname": "Snow"
	},
	{
		"id": 57,
		"name": "Rama",
		"surname": "Jordan"
	},
	{
		"id": 58,
		"name": "Harrison",
		"surname": "Daniels"
	},
	{
		"id": 59,
		"name": "Aurora",
		"surname": "Sheppard"
	},
	{
		"id": 60,
		"name": "Amanda",
		"surname": "Allen"
	},
	{
		"id": 61,
		"name": "Yvonne",
		"surname": "Watson"
	},
	{
		"id": 62,
		"name": "Wallace",
		"surname": "Ramos"
	},
	{
		"id": 63,
		"name": "Jane",
		"surname": "Castillo"
	},
	{
		"id": 64,
		"name": "Genevieve",
		"surname": "Aguirre"
	},
	{
		"id": 65,
		"name": "Alfonso",
		"surname": "Burnett"
	},
	{
		"id": 66,
		"name": "Jeremy",
		"surname": "Christensen"
	},
	{
		"id": 67,
		"name": "Shoshana",
		"surname": "Bentley"
	},
	{
		"id": 68,
		"name": "Allen",
		"surname": "Beck"
	},
	{
		"id": 69,
		"name": "Travis",
		"surname": "Leonard"
	},
	{
		"id": 70,
		"name": "Kyla",
		"surname": "Dorsey"
	},
	{
		"id": 71,
		"name": "Warren",
		"surname": "Bullock"
	},
	{
		"id": 72,
		"name": "Hanna",
		"surname": "Elliott"
	},
	{
		"id": 73,
		"name": "Kadeem",
		"surname": "Hebert"
	},
	{
		"id": 74,
		"name": "Constance",
		"surname": "Lee"
	},
	{
		"id": 75,
		"name": "Mira",
		"surname": "Dillon"
	},
	{
		"id": 76,
		"name": "Carolyn",
		"surname": "Love"
	},
	{
		"id": 77,
		"name": "Kibo",
		"surname": "Matthews"
	},
	{
		"id": 78,
		"name": "Orla",
		"surname": "Dotson"
	},
	{
		"id": 79,
		"name": "Erich",
		"surname": "Goodwin"
	},
	{
		"id": 80,
		"name": "Idona",
		"surname": "Nicholson"
	},
	{
		"id": 81,
		"name": "Merritt",
		"surname": "Bray"
	},
	{
		"id": 82,
		"name": "Nina",
		"surname": "Nicholson"
	},
	{
		"id": 83,
		"name": "Craig",
		"surname": "Joyner"
	},
	{
		"id": 84,
		"name": "Stone",
		"surname": "Wells"
	},
	{
		"id": 85,
		"name": "Ivy",
		"surname": "Dickerson"
	},
	{
		"id": 86,
		"name": "Jasper",
		"surname": "Parker"
	},
	{
		"id": 87,
		"name": "Cullen",
		"surname": "Welch"
	},
	{
		"id": 88,
		"name": "Louis",
		"surname": "Burris"
	},
	{
		"id": 89,
		"name": "Roth",
		"surname": "Schultz"
	},
	{
		"id": 90,
		"name": "Jessamine",
		"surname": "Sellers"
	},
	{
		"id": 91,
		"name": "Paula",
		"surname": "Dunn"
	},
	{
		"id": 92,
		"name": "Vincent",
		"surname": "Poole"
	},
	{
		"id": 93,
		"name": "Joshua",
		"surname": "Vega"
	},
	{
		"id": 94,
		"name": "Gillian",
		"surname": "Holman"
	},
	{
		"id": 95,
		"name": "Slade",
		"surname": "West"
	},
	{
		"id": 96,
		"name": "Lee",
		"surname": "Mccray"
	},
	{
		"id": 97,
		"name": "Rhiannon",
		"surname": "Garrett"
	},
	{
		"id": 98,
		"name": "Cody",
		"surname": "Bray"
	},
	{
		"id": 99,
		"name": "Nehru",
		"surname": "Blackburn"
	},
	{
		"id": 100,
		"name": "Daphne",
		"surname": "Rose"
	}
],
  "address": [
    {"id":1, "person_id":1, "city": "ankara"},
    {"id":2, "person_id":2, "city": "corum"},
    {"id":3, "person_id":3, "city": "ibiza"}
  ]
}
